oslo_policy_remote/__init__.py
oslo_policy_remote/exceptions.py
oslo_policy_remote/generator.py
oslo_policy_remote/opts.py
oslo_policy_remote/remote.py
oslo_policy_remote/shell.py
oslo_policy_remote/version.py
oslo_policy_remote-0.0.3.dev3.dist-info/licenses/AUTHORS
oslo_policy_remote-0.0.3.dev3.dist-info/licenses/LICENSE
oslo_policy_remote-0.0.3.dev3.dist-info/METADATA
oslo_policy_remote-0.0.3.dev3.dist-info/WHEEL
oslo_policy_remote-0.0.3.dev3.dist-info/entry_points.txt
oslo_policy_remote-0.0.3.dev3.dist-info/pbr.json
oslo_policy_remote-0.0.3.dev3.dist-info/top_level.txt
oslo_policy_remote-0.0.3.dev3.dist-info/RECORD
